{
    "client": "Thunder Client",
    "collectionName": "TodoApp",
    "dateExported": "2023-04-22T11:59:40.512Z",
    "version": "1.1",
    "folders": [
        {
            "_id": "8eb4547a-3a46-49e3-9e1f-02e6294259be",
            "name": "CreatUser",
            "containerId": "",
            "created": "2023-04-20T17:05:19.947Z",
            "sortNum": 10000
        },
        {
            "_id": "288ef729-1d5a-401c-9477-c4f3c899ec39",
            "name": "LoginUser",
            "containerId": "",
            "created": "2023-04-20T17:07:01.432Z",
            "sortNum": 20000
        },
        {
            "_id": "893edb08-37f6-4e8a-ab6f-3103a7e26fad",
            "name": "fetchAllTask",
            "containerId": "",
            "created": "2023-04-20T17:21:33.408Z",
            "sortNum": 30000
        },
        {
            "_id": "b74c76dd-f1c6-4e19-b145-ab6ee4cb4877",
            "name": "addTask",
            "containerId": "",
            "created": "2023-04-20T18:03:40.541Z",
            "sortNum": 40000
        }
    ],
    "requests": [
        {
            "_id": "8911ef38-dd3d-4acc-b2c8-a904b134e539",
            "colId": "6ffb07b9-4810-4b55-80e9-de474ad53d1a",
            "containerId": "8eb4547a-3a46-49e3-9e1f-02e6294259be",
            "name": "signUp",
            "url": "http://localhost:8000/api/user/sign-up",
            "method": "POST",
            "sortNum": 10000,
            "created": "2023-04-20T17:05:33.849Z",
            "modified": "2023-04-22T06:58:57.265Z",
            "headers": [
                {
                    "name": "Content-Type",
                    "value": "application/json"
                }
            ],
            "params": [],
            "body": {
                "type": "json",
                "raw": "{\n  \"name\": \"hulk\",\n  \"email\": \"hulk@gmail.com\",\n  \"password\": \"1234567\"\n}",
                "form": []
            },
            "tests": []
        },
        {
            "_id": "7155c64a-c558-4a86-80fd-4de42355c342",
            "colId": "6ffb07b9-4810-4b55-80e9-de474ad53d1a",
            "containerId": "288ef729-1d5a-401c-9477-c4f3c899ec39",
            "name": "Login",
            "url": "http://localhost:8000/api/user/sign-in",
            "method": "POST",
            "sortNum": 20000,
            "created": "2023-04-20T17:07:14.282Z",
            "modified": "2023-04-20T17:08:25.370Z",
            "headers": [
                {
                    "name": "Content-Type",
                    "value": "application/json"
                }
            ],
            "params": [],
            "body": {
                "type": "json",
                "raw": "{\n  \"email\": \"loki@gmail.com\",\n  \"password\": \"1234567\"\n}",
                "form": []
            },
            "tests": []
        },
        {
            "_id": "2c880c5a-5832-46b3-bf80-955adfca81b1",
            "colId": "6ffb07b9-4810-4b55-80e9-de474ad53d1a",
            "containerId": "893edb08-37f6-4e8a-ab6f-3103a7e26fad",
            "name": "fetchalltask",
            "url": "http://localhost:8000/api/user/getTask",
            "method": "GET",
            "sortNum": 30000,
            "created": "2023-04-20T17:22:09.136Z",
            "modified": "2023-04-20T17:23:52.726Z",
            "headers": [
                {
                    "name": "auth-token",
                    "value": "eyJhbGciOiJIUzI1NiIsInR5cCI6IkpXVCJ9.eyJ1c2VyIjp7ImlkIjoiNjQ0MTcxMWMzYzE2MmFmZWY3NjYxNmM1In0sImlhdCI6MTY4MjAxMDUwNX0.vrYRpp5LtsK_N5JbKfVYFkzGKQXLk0Kx4VBgpL0lSEA"
                }
            ],
            "params": [],
            "tests": []
        },
        {
            "_id": "1e2bcf1a-543b-4c21-8d92-6c74787473a8",
            "colId": "6ffb07b9-4810-4b55-80e9-de474ad53d1a",
            "containerId": "b74c76dd-f1c6-4e19-b145-ab6ee4cb4877",
            "name": "addTask",
            "url": "http://localhost:8000/api/task/addtask",
            "method": "POST",
            "sortNum": 40000,
            "created": "2023-04-20T18:03:50.858Z",
            "modified": "2023-04-20T18:07:53.884Z",
            "headers": [
                {
                    "name": "auth-token",
                    "value": "eyJhbGciOiJIUzI1NiIsInR5cCI6IkpXVCJ9.eyJ1c2VyIjp7ImlkIjoiNjQ0MTcxMWMzYzE2MmFmZWY3NjYxNmM1In0sImlhdCI6MTY4MjAxMDUwNX0.vrYRpp5LtsK_N5JbKfVYFkzGKQXLk0Kx4VBgpL0lSEA"
                }
            ],
            "params": [],
            "body": {
                "type": "json",
                "raw": "{\n  \"title\": \"web tech\",\n  \"description\": \"I am good\",\n  \"status\": \"pending\"\n}",
                "form": []
            },
            "tests": []
        },
        {
            "_id": "961cd36c-79b1-4100-a30e-019aaca7edc7",
            "colId": "6ffb07b9-4810-4b55-80e9-de474ad53d1a",
            "containerId": "",
            "name": "daeeteTask",
            "url": "http://localhost:8000/api/task/deletetask/64417fdcf0ed95317d43c7ae",
            "method": "DELETE",
            "sortNum": 50000,
            "created": "2023-04-20T18:21:02.382Z",
            "modified": "2023-04-20T18:22:34.682Z",
            "headers": [
                {
                    "name": "auth-token",
                    "value": "eyJhbGciOiJIUzI1NiIsInR5cCI6IkpXVCJ9.eyJ1c2VyIjp7ImlkIjoiNjQ0MTcxMWMzYzE2MmFmZWY3NjYxNmM1In0sImlhdCI6MTY4MjAxMDUwNX0.vrYRpp5LtsK_N5JbKfVYFkzGKQXLk0Kx4VBgpL0lSEA"
                }
            ],
            "params": [],
            "tests": []
        },
        {
            "_id": "44a5c8b9-ce5d-4b53-858e-92773c4e517f",
            "colId": "6ffb07b9-4810-4b55-80e9-de474ad53d1a",
            "containerId": "",
            "name": "updatetask",
            "url": "http://localhost:8000/api/task/updatetask/6442c4258cdc3f0b060ee698",
            "method": "PUT",
            "sortNum": 60000,
            "created": "2023-04-21T17:13:44.021Z",
            "modified": "2023-04-21T17:19:30.224Z",
            "headers": [
                {
                    "name": "auth-token",
                    "value": "eyJhbGciOiJIUzI1NiIsInR5cCI6IkpXVCJ9.eyJ1c2VyIjp7ImlkIjoiNjQ0MTcxMWMzYzE2MmFmZWY3NjYxNmM1In0sImlhdCI6MTY4MjAxMDUwNX0.vrYRpp5LtsK_N5JbKfVYFkzGKQXLk0Kx4VBgpL0lSEA"
                }
            ],
            "params": [],
            "body": {
                "type": "json",
                "raw": "{\n  \"title\": \"web technology\",\n  \"description\": \"network tech\",\n  \"status\": \"complete\"\n}",
                "form": []
            },
            "tests": []
        }
    ]
}
